jobqueues/__init__.py
jobqueues/celeryqueue.py
jobqueues/config.py
jobqueues/config_lsf.yml
jobqueues/config_slurm.yml
jobqueues/home.py
jobqueues/localqueue.py
jobqueues/logging.ini
jobqueues/lsfqueue.py
jobqueues/pbsqueue.py
jobqueues/playqueue.py
jobqueues/sgequeue.py
jobqueues/simqueue.py
jobqueues/slurmqueue.py
jobqueues/util.py
jobqueues/celeryfiles/Makefile
jobqueues/celeryfiles/__init__.py
jobqueues/celeryfiles/celery.py
jobqueues/celeryfiles/tasks.py
jobqueues/templates/SGE_job.sh.j2
jobqueues/templates/SLURM_job.sh.j2
jobqueues-1.0.13.dist-info/licenses/LICENSE
jobqueues-1.0.13.dist-info/METADATA
jobqueues-1.0.13.dist-info/WHEEL
jobqueues-1.0.13.dist-info/top_level.txt
jobqueues-1.0.13.dist-info/RECORD
