Metadata-Version: 2.4
Name: jobqueues
Version: 1.0.13
Summary: Wrappers for various queueing systems in python
Author-email: Acellera <info@acellera.com>
Project-URL: Homepage, https://github.com/Acellera/jobqueues
Project-URL: Bug Tracker, https://github.com/Acellera/jobqueues/issues
Classifier: Programming Language :: Python :: 3
Classifier: Operating System :: POSIX :: Linux
Requires-Python: >=3.8
License-File: LICENSE
Requires-Dist: protocolinterface
Requires-Dist: psutil
Requires-Dist: pyyaml
Requires-Dist: jinja2
Dynamic: license-file
